elasticityproject/__init__.py
elasticityproject/elasticityproject.py
elasticityproject/plots2d.py
elasticityproject/plots3d.py
elasticityproject-0.2.0.dist-info/LICENSE
elasticityproject-0.2.0.dist-info/WHEEL
elasticityproject-0.2.0.dist-info/METADATA
elasticityproject-0.2.0.dist-info/RECORD
